youtube_transcript_api/__init__.py
youtube_transcript_api/__main__.py
youtube_transcript_api/_api.py
youtube_transcript_api/_cli.py
youtube_transcript_api/_errors.py
youtube_transcript_api/_settings.py
youtube_transcript_api/_transcripts.py
youtube_transcript_api/_transcripts.py.orig
youtube_transcript_api/formatters.py
youtube_transcript_api/proxies.py
youtube_transcript_api/py.typed
youtube_transcript_api/test/__init__.py
youtube_transcript_api/test/assets/__init__.py
youtube_transcript_api/test/assets/transcript.xml.static
youtube_transcript_api/test/assets/youtube.html.static
youtube_transcript_api/test/assets/youtube.innertube.json.static
youtube_transcript_api/test/assets/youtube_age_restricted.innertube.json.static
youtube_transcript_api/test/assets/youtube_altered_user_agent.innertube.json.static
youtube_transcript_api/test/assets/youtube_consent_page.html.static
youtube_transcript_api/test/assets/youtube_consent_page_invalid.html.static
youtube_transcript_api/test/assets/youtube_po_token_required.innertube.json.static
youtube_transcript_api/test/assets/youtube_request_blocked.innertube.json.static
youtube_transcript_api/test/assets/youtube_too_many_requests.html.static
youtube_transcript_api/test/assets/youtube_transcripts_disabled.innertube.json.static
youtube_transcript_api/test/assets/youtube_transcripts_disabled2.innertube.json.static
youtube_transcript_api/test/assets/youtube_unplayable.innertube.json.static
youtube_transcript_api/test/assets/youtube_video_unavailable.innertube.json.static
youtube_transcript_api/test/assets/youtube_ww1_nl_en.innertube.json.static
youtube_transcript_api/test/test_api.py
youtube_transcript_api/test/test_cli.py
youtube_transcript_api/test/test_formatters.py
youtube_transcript_api/test/test_proxies.py
ytranscripting-1.1.1.1.dist-info/LICENSE
ytranscripting-1.1.1.1.dist-info/METADATA
ytranscripting-1.1.1.1.dist-info/WHEEL
ytranscripting-1.1.1.1.dist-info/entry_points.txt
ytranscripting-1.1.1.1.dist-info/RECORD
