Metadata-Version: 2.3
Name: ytranscripting
Version: 1.1.1.1
Summary: ytranscripting
License: MIT
Keywords: cli,subtitle,subtitles,transcript,transcripts,youtube,youtube-api,youtube-subtitles,youtube-transcripts
Author: Jonas Depoix
Author-email: jonas.depoix@web.de
Requires-Python: >=3.8,<3.14
Classifier: License :: OSI Approved :: MIT License
Classifier: Operating System :: OS Independent
Classifier: Programming Language :: Python :: 3
Classifier: Programming Language :: Python :: 3.8
Classifier: Programming Language :: Python :: 3.9
Classifier: Programming Language :: Python :: 3.10
Classifier: Programming Language :: Python :: 3.11
Classifier: Programming Language :: Python :: 3.12
Classifier: Programming Language :: Python :: 3.13
Requires-Dist: defusedxml (>=0.7.1,<0.8.0)
Requires-Dist: requests
Project-URL: Homepage, https://github.com/TheDevelopmentMachine/ytranscripting
Project-URL: Repository, https://github.com/TheDevelopmentMachine/ytranscripting
